python_access_modifiers/__init__.py
python_access_modifiers/_constant_modifier.py
python_access_modifiers/_field_modifiers.py
python_access_modifiers/_private_modifier.py
python_access_modifiers/_protected_modifier.py
python_access_modifiers-1.3.1.dist-info/METADATA
python_access_modifiers-1.3.1.dist-info/WHEEL
python_access_modifiers-1.3.1.dist-info/licenses/LICENSE
python_access_modifiers-1.3.1.dist-info/RECORD
