Metadata-Version: 2.1
Name: python-access-modifiers
Version: 1.3.1
Summary: Python decorators to specify accessible scopes and enhance access control of methods.
Author: mxngo
License-File: LICENSE
Classifier: Development Status :: 5 - Production/Stable
Classifier: License :: OSI Approved :: MIT License
Classifier: Operating System :: OS Independent
Classifier: Programming Language :: Python :: 3
Classifier: Topic :: Utilities
Requires-Python: >=3.12
